jtexport/__init__.py
jtexport/cli.py
jtexport/exporter.py
jtexport-0.1.0.dist-info/licenses/LICENSE
jtexport-0.1.0.dist-info/METADATA
jtexport-0.1.0.dist-info/WHEEL
jtexport-0.1.0.dist-info/entry_points.txt
jtexport-0.1.0.dist-info/top_level.txt
jtexport-0.1.0.dist-info/RECORD
