Metadata-Version: 2.4
Name: jtexport
Version: 0.1.0
Summary: Export #export cells from Jupytext (py:percent) files into clean modules
Author: Assefa Seyoum
License: MIT
Classifier: Programming Language :: Python :: 3
Classifier: License :: OSI Approved :: MIT License
Classifier: Operating System :: OS Independent
Requires-Python: >=3.8
License-File: LICENSE
Dynamic: license-file
